<?xml version="1.0" encoding="UTF-8"?>

<mule xmlns:ee="http://www.mulesoft.org/schema/mule/ee/core" xmlns:db="http://www.mulesoft.org/schema/mule/db"
	xmlns:http="http://www.mulesoft.org/schema/mule/http"
	xmlns="http://www.mulesoft.org/schema/mule/core" xmlns:doc="http://www.mulesoft.org/schema/mule/documentation" xmlns:xsi="http://www.w3.org/2001/XMLSchema-instance" xsi:schemaLocation="http://www.mulesoft.org/schema/mule/core http://www.mulesoft.org/schema/mule/core/current/mule.xsd
http://www.mulesoft.org/schema/mule/http http://www.mulesoft.org/schema/mule/http/current/mule-http.xsd
http://www.mulesoft.org/schema/mule/db http://www.mulesoft.org/schema/mule/db/current/mule-db.xsd
http://www.mulesoft.org/schema/mule/ee/core http://www.mulesoft.org/schema/mule/ee/core/current/mule-ee.xsd">
	<http:listener-config name="HTTP_Listener_config" doc:name="HTTP Listener config" doc:id="06718005-4609-44d0-96b6-5173afb4158e" >
		<http:listener-connection host="0.0.0.0" port="8081" />
	</http:listener-config>
	<db:config name="Database_Config" doc:name="Database Config" doc:id="84faa0b9-6e06-4daf-be10-fac76fc71e23" >
		<db:my-sql-connection host="mudb.learn.mulesoft.com" port="3306" user="mule" password="mule" database="training" />
	</db:config>
	<db:config name="Database_Config1" doc:name="Database Config" doc:id="a9a400cc-2356-4257-b3c0-5603c62f4e3a" >
		<db:my-sql-connection host="mudb.learn.mulesoft.com" port="3306" user="mule" password="mule" database="training" />
	</db:config>
	<flow name="dw-tutorial-flights-wsFlow" doc:id="f3b6dee2-9123-4cba-a241-d7f2aae74eaa" >
		<http:listener doc:name="Listener" doc:id="b2ef625c-a0b6-4147-b324-8a0a7125c94a" config-ref="HTTP_Listener_config" path="/flights"/>
		<db:select doc:name="Select" doc:id="61a63eab-61f1-447d-b801-44be97944ec5" config-ref="Database_Config1">
			<db:sql ><![CDATA[SELECT * FROM american]]></db:sql>
		</db:select>
		<ee:transform doc:name="Transform Message" doc:id="87ae3cee-f2ef-41ea-9b9d-6d8ee0ba5d11" >
			<ee:message >
				<ee:set-payload ><![CDATA[%dw 2.0
output application/json
---
payload]]></ee:set-payload>
			</ee:message>
		</ee:transform>
	</flow>
</mule>
